CHANGELOG.txt
LICENCE.txt
MANIFEST.in
README.txt
setup.py
fibonacci/__init__.py
some1fibonacci.egg-info/PKG-INFO
some1fibonacci.egg-info/SOURCES.txt
some1fibonacci.egg-info/dependency_links.txt
some1fibonacci.egg-info/top_level.txt